Metadata-Version: 2.1
Name: pyspeechkit
Version: 1.0.0
Summary: Library for working with a range of technologies for speech recognition and synthesis from Yandex (Speechkit).
Home-page: https://github.com/pystorage/pyspeechkit
Author: Master
Author-email: 
License: MIT
Platform: UNKNOWN
